.coveragerc
.travis.yml
AUTHORS
ChangeLog
LICENSE
MANIFEST.in
README.rst
requirements.txt
setup.cfg
setup.py
tox.ini
docs/Makefile
docs/make.bat
docs/source/conf.py
docs/source/index.rst
docs/source/readme.rst
leonardo_admin_dashboard/__init__.py
leonardo_admin_dashboard/dashboard.py
leonardo_admin_dashboard/menu.py
leonardo_admin_dashboard/modules.py
leonardo_admin_dashboard/settings.py
leonardo_admin_dashboard/urls.py
leonardo_admin_dashboard.egg-info/PKG-INFO
leonardo_admin_dashboard.egg-info/SOURCES.txt
leonardo_admin_dashboard.egg-info/dependency_links.txt
leonardo_admin_dashboard.egg-info/not-zip-safe
leonardo_admin_dashboard.egg-info/pbr.json
leonardo_admin_dashboard.egg-info/requires.txt
leonardo_admin_dashboard.egg-info/top_level.txt
leonardo_admin_dashboard/dashboard_modules/__init__.py
leonardo_admin_dashboard/dashboard_modules/dummy.py
leonardo_admin_dashboard/dashboard_modules/google_analytics.py
leonardo_admin_dashboard/dashboard_modules/lists.py
leonardo_admin_dashboard/locale/cs/LC_MESSAGES/django.po
leonardo_admin_dashboard/locale/en/LC_MESSAGES/django.po
leonardo_admin_dashboard/static/feincms/item_editor.css
leonardo_admin_dashboard/static/feincms/item_editor.js
leonardo_admin_dashboard/static/feincms/tree_editor.css
leonardo_admin_dashboard/templates/admin/base.html
leonardo_admin_dashboard/templates/admin/change_form.html
leonardo_admin_dashboard/templates/admin/login.html
leonardo_admin_dashboard/templates/admin/sidebar_menu.html
leonardo_admin_dashboard/templates/admin/constance/change_list.html
leonardo_admin_dashboard/templates/admin/feincms/content_editor_with_go.html
leonardo_admin_dashboard/templates/admin/feincms/fieldset.html
leonardo_admin_dashboard/templates/admin/feincms/item_editor.html
leonardo_admin_dashboard/templates/dashboard/base.html
leonardo_admin_dashboard/templates/dashboard/index.html
leonardo_admin_dashboard/templates/dashboard/layout.html
leonardo_admin_dashboard/templates/dashboard/modules/_menu_model_list.html
leonardo_admin_dashboard/templates/dashboard/modules/_submenu_app_list.html
leonardo_admin_dashboard/templates/dashboard/modules/_submenu_link_list.html
leonardo_admin_dashboard/templates/dashboard/modules/dummy_visitors.html
leonardo_admin_dashboard/templates/dashboard/modules/dummy_visitors_chart.html
